dash_okta_oauth2/__init__.py
dash_okta_oauth2/auth.py
dash_okta_oauth2/okta_oauth.py
dash_okta_oauth2-0.0.2.dist-info/LICENSE.md
dash_okta_oauth2-0.0.2.dist-info/METADATA
dash_okta_oauth2-0.0.2.dist-info/WHEEL
dash_okta_oauth2-0.0.2.dist-info/top_level.txt
dash_okta_oauth2-0.0.2.dist-info/RECORD
