Metadata-Version: 2.1
Name: dash-okta-oauth2
Version: 0.0.2
Summary: Dash Okta OAuth2
Home-page: https://github.com/nicohein/dash-okta-oauth2
Author: Nico Hein
Author-email: nico.hein@me.com
License: MIT
Platform: UNKNOWN
Classifier: License :: OSI Approved :: MIT License
Classifier: Operating System :: OS Independent
Classifier: Programming Language :: Python :: 3
Requires-Python: >=3.7
Requires-Dist: dash (>=1.9.1)
Requires-Dist: dash-core-components (>=1.8.1)
Requires-Dist: dash-html-components (>=1.0.2)
Requires-Dist: Flask (>=1.1.1)
Requires-Dist: Flask-Dance (>=3.0.0)
Requires-Dist: blinker (>=1.4)
